setup.cfg
setup.py
aead/__init__.py
aead.egg-info/PKG-INFO
aead.egg-info/SOURCES.txt
aead.egg-info/dependency_links.txt
aead.egg-info/requires.txt
aead.egg-info/top_level.txt